wled_adapter/__init__.py
wled_adapter/adapter.py
wled_adapter/connection.py
wled_adapter/segment.py
wled_adapter/state.py
wled_adapter-0.0.6.dist-info/LICENSE
wled_adapter-0.0.6.dist-info/METADATA
wled_adapter-0.0.6.dist-info/WHEEL
wled_adapter-0.0.6.dist-info/RECORD
