Metadata-Version: 2.1
Name: wled-adapter
Version: 0.0.6
Summary: A package to interact with WLED devices
Home-page: https://www.github.com/alessiomorale/wled-adapter
License: MIT
Author: Alessio Morale
Author-email: alessiomorale@gmail.com
Requires-Python: >=3.9,<4.0
Classifier: License :: OSI Approved :: MIT License
Classifier: Programming Language :: Python :: 3
Classifier: Programming Language :: Python :: 3.9
Classifier: Programming Language :: Python :: 3.10
Classifier: Programming Language :: Python :: 3.11
Classifier: Programming Language :: Python :: 3.12
Classifier: Programming Language :: Python :: 3.13
Requires-Dist: colour (>=0.1.5,<0.2.0)
Requires-Dist: dataclasses-json (>=0.6.6,<0.7.0)
Requires-Dist: loguru (>=0.7.2,<0.8.0)
Requires-Dist: pyserial (>=3.5,<4.0)
Project-URL: Repository, https://www.github.com/alessiomorale/wled-adapter
